AUTHORS.rst
CONTRIBUTING.rst
HISTORY.rst
LICENSE
MANIFEST.in
README.rst
requirements.txt
setup.cfg
setup.py
docs/Makefile
docs/authors.rst
docs/conf.py
docs/contributing.rst
docs/history.rst
docs/index.rst
docs/installation.rst
docs/make.bat
docs/readme.rst
docs/usage.rst
sympy_to_c/__init__.py
sympy_to_c/core.py
sympy_to_c.egg-info/PKG-INFO
sympy_to_c.egg-info/SOURCES.txt
sympy_to_c.egg-info/dependency_links.txt
sympy_to_c.egg-info/not-zip-safe
sympy_to_c.egg-info/requires.txt
sympy_to_c.egg-info/top_level.txt
tests/__init__.py
tests/sp2clib.c
tests/sp2clib.o
tests/test_sympy_to_c.py