Metadata-Version: 1.1
Name: sympy-to-c
Version: 0.1.2
Summary: Simple library to create importable C-functions from sympy-Expressions
Home-page: https://github.com/cknoll/sympy_to_c
Author: Carsten Knoll
Author-email: carsten.knoll@poste.de
License: GNU General Public License v3
Keywords: sympy_to_c
Platform: UNKNOWN
Classifier: Development Status :: 4 - Beta
Classifier: Intended Audience :: Developers
Classifier: License :: OSI Approved :: GNU General Public License v3 (GPLv3)
Classifier: Natural Language :: English
Classifier: Programming Language :: Python :: 2
Classifier: Programming Language :: Python :: 2.7
Classifier: Programming Language :: Python :: 3
Classifier: Programming Language :: Python :: 3.4
Classifier: Programming Language :: Python :: 3.5
Classifier: Programming Language :: Python :: 3.6
